odoo10_addon_l10n_es_aeat_mod303_cash_basis-10.0.2.0.0-py2.7-nspkg.pth
odoo/addons/l10n_es_aeat_mod303_cash_basis/README.rst
odoo/addons/l10n_es_aeat_mod303_cash_basis/__init__.py
odoo/addons/l10n_es_aeat_mod303_cash_basis/__manifest__.py
odoo/addons/l10n_es_aeat_mod303_cash_basis/data/aeat_export_mod303_2018_data.xml
odoo/addons/l10n_es_aeat_mod303_cash_basis/data/tax_code_map_mod303_data.xml
odoo/addons/l10n_es_aeat_mod303_cash_basis/i18n/es.po
odoo/addons/l10n_es_aeat_mod303_cash_basis/models/__init__.py
odoo/addons/l10n_es_aeat_mod303_cash_basis/models/account_partial_reconcile.py
odoo/addons/l10n_es_aeat_mod303_cash_basis/models/mod303.py
odoo/addons/l10n_es_aeat_mod303_cash_basis/static/description/icon.png
odoo/addons/l10n_es_aeat_mod303_cash_basis/static/description/icon_source.svg
odoo/addons/l10n_es_aeat_mod303_cash_basis/tests/__init__.py
odoo/addons/l10n_es_aeat_mod303_cash_basis/tests/test_l10n_es_aeat_mod303_cash_basis.py
odoo/addons/l10n_es_aeat_mod303_cash_basis/views/mod303_view.xml
odoo10_addon_l10n_es_aeat_mod303_cash_basis-10.0.2.0.0.dist-info/DESCRIPTION.rst
odoo10_addon_l10n_es_aeat_mod303_cash_basis-10.0.2.0.0.dist-info/METADATA
odoo10_addon_l10n_es_aeat_mod303_cash_basis-10.0.2.0.0.dist-info/RECORD
odoo10_addon_l10n_es_aeat_mod303_cash_basis-10.0.2.0.0.dist-info/WHEEL
odoo10_addon_l10n_es_aeat_mod303_cash_basis-10.0.2.0.0.dist-info/metadata.json
odoo10_addon_l10n_es_aeat_mod303_cash_basis-10.0.2.0.0.dist-info/namespace_packages.txt
odoo10_addon_l10n_es_aeat_mod303_cash_basis-10.0.2.0.0.dist-info/top_level.txt
